{"is_source_file": false, "format": "", "description": "", "external_files": [], "external_methods": [], "published": [], "classes": [], "methods": [], "calls": [], "search-terms": [], "state": 2, "file_id": 11, "knowledge_revision": 128, "git_revision": "1d8e529b80c278f6e8a830ced4279fd3212cb521", "hash": "187ef7186eb936dd394ef331d2c044e5", "format-version": 4, "code-base-name": "android_tv_frontend", "filename": "android_tv_frontend/app/src/main/res/values/colors.xml", "revision_history": [{"128": "1d8e529b80c278f6e8a830ced4279fd3212cb521"}]}